seele_sdk/__init__.py
seele_sdk/agent.py
seele_sdk-0.1.6.dist-info/licenses/LICENSE
seele_sdk-0.1.6.dist-info/METADATA
seele_sdk-0.1.6.dist-info/WHEEL
seele_sdk-0.1.6.dist-info/top_level.txt
seele_sdk-0.1.6.dist-info/RECORD
